{
    "js": [
        "js/columnControl.semanticui.js",
        "js/columnControl.semanticui.min.js",
        "js/columnControl.semanticui.min.mjs",
        "js/columnControl.semanticui.mjs"
    ],
    "css": [
        "css/columnControl.semanticui.css",
        "css/columnControl.semanticui.min.css"
    ],
    "types": [
        "types/columnControl.semanticui.d.ts"
    ],
    "src-repo": "http://github.com/DataTables/ColumnControl",
    "last-tag": "1.0.7",
    "last-sync": "f6c3dff0b93e8e54de239885fba177366568a037"
}