{
    "js": [
        "js/columnControl.semanticui.js",
        "js/columnControl.semanticui.min.js",
        "js/columnControl.semanticui.min.mjs",
        "js/columnControl.semanticui.mjs"
    ],
    "css": [
        "css/columnControl.semanticui.css",
        "css/columnControl.semanticui.min.css"
    ],
    "types": [
        "types/columnControl.semanticui.d.ts"
    ],
    "src-repo": "http://github.com/DataTables/ColumnControl",
    "last-tag": "1.0.7",
    "last-sync": "f2c9c1fce06bbc60d326210290d2d053d6747bdc"
}